ipyvasp/__init__.py
ipyvasp/__main__.py
ipyvasp/_enplots.py
ipyvasp/_lattice.py
ipyvasp/_version.py
ipyvasp/bsdos.py
ipyvasp/cli.py
ipyvasp/evals_dataframe.py
ipyvasp/lattice.py
ipyvasp/misc.py
ipyvasp/potential.py
ipyvasp/surface.py
ipyvasp/utils.py
ipyvasp/widgets.py
ipyvasp/core/__init__.py
ipyvasp/core/parser.py
ipyvasp/core/plot_toolkit.py
ipyvasp/core/serializer.py
ipyvasp/core/spatial_toolkit.py
ipyvasp-1.1.6.dist-info/LICENSE
ipyvasp-1.1.6.dist-info/METADATA
ipyvasp-1.1.6.dist-info/WHEEL
ipyvasp-1.1.6.dist-info/entry_points.txt
ipyvasp-1.1.6.dist-info/top_level.txt
ipyvasp-1.1.6.dist-info/RECORD
