Metadata-Version: 2.1
Name: ipyvasp
Version: 1.1.6
Summary: A processing tool for VASP DFT input/output processing in Jupyter Notebook.
Home-page: https://github.com/massgh/ipyvasp
Author: Abdul Saboor
Author-email: mass_qau@outlook.com
License: MIT
Project-URL: Bug Tracker, https://github.com/massgh/ipyvasp/issues
Keywords: Jupyter,Widgets,IPython,VASP,DFT
Platform: UNKNOWN
Classifier: License :: OSI Approved :: MIT License
Classifier: Programming Language :: Python :: 3
Classifier: Operating System :: OS Independent
Requires-Python: >=3.9
License-File: LICENSE
Requires-Dist: matplotlib>=3.7.5
Requires-Dist: numpy>=1.23.2
Requires-Dist: scipy>=1.9.1
Requires-Dist: ipywidgets>=8.0.4
Requires-Dist: pillow>=9.3.0
Requires-Dist: pandas>=1.4.4
Requires-Dist: plotly>=6.2.0
Requires-Dist: requests>=2.28.1
Requires-Dist: typer>=0.9.0
Requires-Dist: dashlab
Requires-Dist: sympy
Provides-Extra: extra
Requires-Dist: jupyterlab>=3.5.2; extra == "extra"
Requires-Dist: ipython>=9.0; extra == "extra"
Requires-Dist: ase>=3.22.1; extra == "extra"
Requires-Dist: nglview>=3.0.4; extra == "extra"
